[
    {
        "name": "Bauerntoast Speck-Käse",
        "price": 9.5,
        "deposit": 0.0,
        "color": "Orange"
    },
    {
        "name": "Bauerntoast Käse",
        "price": 9.5,
        "deposit": 0.0,
        "color": "Orange"
    },
    {
        "name": "Glühwein",
        "price": 4.5,
        "deposit": 4.0,
        "color": "Orange"
    },
    {
        "name": "Glühmost",
        "price": 4.0,
        "deposit": 4.0,
        "color": "Orange"
    },
    {
        "name": "Bratapfel Punsch",
        "price": 3.5,
        "deposit": 4.0,
        "color": "Orange"
    },
    {
        "name": "Punsch mit Schuss",
        "price": 4.5,
        "deposit": 4.0,
        "color": "Orange"
    },
    {
        "name": "Bier",
        "price": 3.5,
        "deposit": 0.0,
        "color": "Orange"
    },
    {
        "name": "Spritzer",
        "price": 4.0,
        "deposit": 0.0,
        "color": "Orange"
    },
    {
        "name": "Limo",
        "price": 3.5,
        "deposit": 0.0,
        "color": "Orange"
    },
    {
        "name": "Mineral",
        "price": 3.0,
        "deposit": 0.0,
        "color": "Orange"
    },
    {
        "name": "Eierlikör in Waffelbecher",
        "price": 4.0,
        "deposit": 0.0,
        "color": "Orange"
    }
]
